laibon/__init__.py
laibon/accessor.py
laibon/activity.py
laibon/common.py
laibon/db.py
laibon/exception.py
laibon/rest.py
laibon/rtf.py
laibon-0.0.12.dist-info/METADATA
laibon-0.0.12.dist-info/WHEEL
laibon-0.0.12.dist-info/licenses/LICENSE
laibon-0.0.12.dist-info/RECORD
