Metadata-Version: 2.4
Name: laibon
Version: 0.0.12
Summary: Common library for django development
Author-email: Wenceslaus Mumala <info@dvectors.com>
License-File: LICENSE
Classifier: License :: OSI Approved :: MIT License
Classifier: Operating System :: OS Independent
Classifier: Programming Language :: Python :: 3
Requires-Python: >=3.8
Requires-Dist: django>=4.2
Requires-Dist: jsonschema>=4.0.0
